muxi/__init__.py
muxi_ai-0.0.1.dist-info/LICENSE.txt
muxi_ai-0.0.1.dist-info/METADATA
muxi_ai-0.0.1.dist-info/WHEEL
muxi_ai-0.0.1.dist-info/top_level.txt
muxi_ai-0.0.1.dist-info/RECORD
